odoo/addons/ssi_transaction_cancel_mixin/README.rst
odoo/addons/ssi_transaction_cancel_mixin/__init__.py
odoo/addons/ssi_transaction_cancel_mixin/__manifest__.py
odoo/addons/ssi_transaction_cancel_mixin/demo/base_cancel_reason_demo.xml
odoo/addons/ssi_transaction_cancel_mixin/i18n/ssi_transaction_cancel_mixin.pot
odoo/addons/ssi_transaction_cancel_mixin/models/__init__.py
odoo/addons/ssi_transaction_cancel_mixin/models/base_cancel_reason.py
odoo/addons/ssi_transaction_cancel_mixin/models/ir_model.py
odoo/addons/ssi_transaction_cancel_mixin/models/mixin_transaction_cancel.py
odoo/addons/ssi_transaction_cancel_mixin/security/ir.model.access.csv
odoo/addons/ssi_transaction_cancel_mixin/static/description/icon.png
odoo/addons/ssi_transaction_cancel_mixin/templates/mixin_transaction_cancel_templates.xml
odoo/addons/ssi_transaction_cancel_mixin/views/base_cancel_reason_views.xml
odoo/addons/ssi_transaction_cancel_mixin/views/ir_model_views.xml
odoo/addons/ssi_transaction_cancel_mixin/wizards/__init__.py
odoo/addons/ssi_transaction_cancel_mixin/wizards/base_select_cancel_reason.py
odoo/addons/ssi_transaction_cancel_mixin/wizards/base_select_cancel_reason_views.xml
odoo14_addon_ssi_transaction_cancel_mixin-14.0.1.13.1.dist-info/METADATA
odoo14_addon_ssi_transaction_cancel_mixin-14.0.1.13.1.dist-info/WHEEL
odoo14_addon_ssi_transaction_cancel_mixin-14.0.1.13.1.dist-info/top_level.txt
odoo14_addon_ssi_transaction_cancel_mixin-14.0.1.13.1.dist-info/RECORD
